{
    "apiVersion": "apps/v1",
    "kind": "Deployment",
    "metadata": {
        "labels": {
            "app": "inventory-api",
            "global-hub.open-cluster-management.io/managed-by": "global-hub-operator"
        },
        "name": "inventory-api",
        "namespace": "multicluster-global-hub",
        "ownerReferences": [
            {
                "apiVersion": "operator.open-cluster-management.io/v1alpha4",
                "blockOwnerDeletion": true,
                "controller": true,
                "kind": "MulticlusterGlobalHub",
                "name": "multiclusterglobalhub",
                "uid": "19497c00-9190-4e8a-853b-c9b168253931"
            }
        ]
    },
    "spec": {
        "replicas": 2,
        "selector": {
            "matchLabels": {
                "app": "inventory-api"
            }
        },
        "template": {
            "metadata": {
                "labels": {
                    "app": "inventory-api"
                }
            },
            "spec": {
                "containers": [
                    {
                        "command": [
                            "/usr/local/bin/inventory-api",
                            "serve"
                        ],
                        "env": [
                            {
                                "name": "POD_NAMESPACE",
                                "valueFrom": {
                                    "fieldRef": {
                                        "apiVersion": "v1",
                                        "fieldPath": "metadata.namespace"
                                    }
                                }
                            },
                            {
                                "name": "INVENTORY_API_CONFIG",
                                "value": "/inventory/inventory-api-config.yaml"
                            }
                        ],
                        "image": "quay.io/stolostron/inventory-api:latest",
                        "imagePullPolicy": "Always",
                        "livenessProbe": {
                            "httpGet": {
                                "path": "/api/inventory/v1/livez",
                                "port": 8081,
                                "scheme": "HTTPS"
                            },
                            "initialDelaySeconds": 15,
                            "periodSeconds": 20
                        },
                        "name": "inventory-api",
                        "ports": [
                            {
                                "containerPort": 8081,
                                "name": "http-server",
                                "protocol": "TCP"
                            },
                            {
                                "containerPort": 9081,
                                "name": "grpc-server",
                                "protocol": "TCP"
                            }
                        ],
                        "readinessProbe": {
                            "httpGet": {
                                "path": "/api/inventory/v1/readyz",
                                "port": 8081,
                                "scheme": "HTTPS"
                            },
                            "initialDelaySeconds": 5,
                            "periodSeconds": 10
                        },
                        "volumeMounts": [
                            {
                                "mountPath": "/inventory",
                                "name": "config-volume",
                                "readOnly": true
                            },
                            {
                                "mountPath": "/inventory/certs",
                                "name": "server-certs",
                                "readOnly": true
                            },
                            {
                                "mountPath": "/inventory/client-certs",
                                "name": "client-ca",
                                "readOnly": true
                            },
                            {
                                "mountPath": "/inventory/kafka-certs",
                                "name": "kafka-certs",
                                "readOnly": true
                            }
                        ]
                    }
                ],
                "initContainers": [
                    {
                        "command": [
                            "/usr/local/bin/inventory-api",
                            "migrate"
                        ],
                        "env": [
                            {
                                "name": "INVENTORY_API_CONFIG",
                                "value": "/inventory/inventory-api-config.yaml"
                            }
                        ],
                        "image": "quay.io/stolostron/inventory-api:latest",
                        "imagePullPolicy": "Always",
                        "name": "migration",
                        "resources": {
                            "requests": {
                                "cpu": "1m",
                                "memory": "20Mi"
                            }
                        },
                        "volumeMounts": [
                            {
                                "mountPath": "/inventory",
                                "name": "config-volume",
                                "readOnly": true
                            }
                        ]
                    }
                ],
                "nodeSelector": null,
                "serviceAccountName": "inventory-api",
                "tolerations": null,
                "volumes": [
                    {
                        "name": "config-volume",
                        "secret": {
                            "secretName": "inventory-api-config"
                        }
                    },
                    {
                        "name": "server-certs",
                        "secret": {
                            "secretName": "inventory-api-server-certs"
                        }
                    },
                    {
                        "name": "client-ca",
                        "secret": {
                            "secretName": "inventory-api-client-ca-certs"
                        }
                    },
                    {
                        "name": "kafka-certs",
                        "secret": {
                            "secretName": "inventory-api-kafka-certs"
                        }
                    }
                ]
            }
        }
    }
}